glpic/__init__.py
glpic/cli.py
glpic/mcp_server.py
glpic-99.0.202511050914.dist-info/METADATA
glpic-99.0.202511050914.dist-info/WHEEL
glpic-99.0.202511050914.dist-info/entry_points.txt
glpic-99.0.202511050914.dist-info/top_level.txt
glpic-99.0.202511050914.dist-info/RECORD
