Metadata-Version: 2.4
Name: glpic
Version: 99.0.202511050914
Summary: GLPI client
Author-email: Karim Boumedhel <karimboumedhel@gmail.com>
License: ASL
Project-URL: Homepage, http://github.com/karmab/glpic
Requires-Dist: fastmcp
Requires-Dist: prettytable
